kukai/__init__.py
kukai/cli.py
kukai/cli_util.py
kukai/config.py
kukai/context.py
kukai/core.py
kukai/engine.py
kukai/helper.py
kukai/util.py
kukai-0.1.1.dist-info/METADATA
kukai-0.1.1.dist-info/WHEEL
kukai-0.1.1.dist-info/entry_points.txt
kukai-0.1.1.dist-info/licenses/LICENSE
kukai-0.1.1.dist-info/RECORD
