Metadata-Version: 2.4
Name: kukai
Version: 0.1.1
Summary: A simple command line interface to manage your templates
Author-email: Caspar Trittibach <ctrittibach@gmail.com>
License-File: LICENSE
Requires-Python: >=3.10
Requires-Dist: click>=8.1.7
Requires-Dist: cookiecutter>=2.6.0
Requires-Dist: inquirer>=3.4.0
Requires-Dist: jinja2>=3.1.5
Requires-Dist: python-levenshtein>=0.27.1
Requires-Dist: toml>=0.10.2
Requires-Dist: typing-extensions; python_version < '3.11'
